Metadata-Version: 2.1
Name: webtorrent-checker-scraper
Version: 1.0
Summary: A simple script to scrape results of WebTorrent Checker (https://checker.openwebtorrent.com)
Home-page: https://github.com/maaaaz/webtorrent-checker-scraper
Author: Thomas D.
Author-email: tdebize@mail.com
License: LGPL
Keywords: webtorrent checker torrent magnet
Platform: UNKNOWN
Classifier: Topic :: Security
Classifier: Development Status :: 5 - Production/Stable
Classifier: Intended Audience :: Information Technology
Classifier: License :: OSI Approved :: GNU Library or Lesser General Public License (LGPL)
Classifier: Programming Language :: Python :: 3
Requires-Python: >=3
